self_healing/__init__.py
self_healing/core.py
self_healing/patcher.py
self_healing/runner.py
self_healing-0.1.2.dist-info/LICENSE
self_healing-0.1.2.dist-info/METADATA
self_healing-0.1.2.dist-info/WHEEL
self_healing-0.1.2.dist-info/top_level.txt
self_healing-0.1.2.dist-info/RECORD
