Metadata-Version: 2.1
Name: self_healing
Version: 0.1.2
Summary: The Self-Healing Library is a Python tool that dynamically runs and patches code to recover from runtime errors using installed data.
Home-page: https://github.com/pythonAndCplusplus/self_healing
Author: Arsam
Author-email: ashouriarsamold@gmail.com
Classifier: Programming Language :: Python :: 3
Classifier: License :: OSI Approved :: MIT License
Classifier: Operating System :: OS Independent
Requires-Python: >=3.6
License-File: LICENSE
Requires-Dist: prompt-toolkit
